Products.CMFPlone-6.1.3-py3.13-nspkg.pth
Products/CMFPlone/ActionsTool.py
Products/CMFPlone/CatalogTool.py
Products/CMFPlone/MigrationTool.py
Products/CMFPlone/PasswordResetTool.py
Products/CMFPlone/PloneBaseTool.py
Products/CMFPlone/PloneBatch.py
Products/CMFPlone/PloneControlPanel.py
Products/CMFPlone/PloneTool.py
Products/CMFPlone/Portal.py
Products/CMFPlone/RegistrationTool.py
Products/CMFPlone/SkinsTool.py
Products/CMFPlone/TranslationServiceTool.py
Products/CMFPlone/TypesTool.py
Products/CMFPlone/URLTool.py
Products/CMFPlone/WorkflowTool.py
Products/CMFPlone/__init__.py
Products/CMFPlone/bbb.py
Products/CMFPlone/catalog.zcml
Products/CMFPlone/configure.zcml
Products/CMFPlone/defaultpage.py
Products/CMFPlone/events.py
Products/CMFPlone/factory.py
Products/CMFPlone/i18nl10n.py
Products/CMFPlone/index.gif
Products/CMFPlone/log.py
Products/CMFPlone/meta.zcml
Products/CMFPlone/overrides.zcml
Products/CMFPlone/permissions.py
Products/CMFPlone/profiles.zcml
Products/CMFPlone/relationhelper.py
Products/CMFPlone/setuphandlers.py
Products/CMFPlone/testing.py
Products/CMFPlone/tool.gif
Products/CMFPlone/traversal.py
Products/CMFPlone/unicodeconflictresolver.py
Products/CMFPlone/utils.py
Products/CMFPlone/workflow.py
Products/CMFPlone/UnicodeSplitter/__init__.py
Products/CMFPlone/UnicodeSplitter/config.py
Products/CMFPlone/UnicodeSplitter/splitter.py
Products/CMFPlone/browser/__init__.py
Products/CMFPlone/browser/admin.py
Products/CMFPlone/browser/admin.zcml
Products/CMFPlone/browser/atd.py
Products/CMFPlone/browser/author.py
Products/CMFPlone/browser/caching.zcml
Products/CMFPlone/browser/configure.zcml
Products/CMFPlone/browser/contact_info.py
Products/CMFPlone/browser/defaultpage.py
Products/CMFPlone/browser/exceptions.py
Products/CMFPlone/browser/favicon.py
Products/CMFPlone/browser/global_statusmessage.py
Products/CMFPlone/browser/icons.py
Products/CMFPlone/browser/interfaces.py
Products/CMFPlone/browser/main_template.py
Products/CMFPlone/browser/navigation.py
products_cmfplone-6.1.3.dist-info/LICENSE
products_cmfplone-6.1.3.dist-info/METADATA
products_cmfplone-6.1.3.dist-info/WHEEL
products_cmfplone-6.1.3.dist-info/namespace_packages.txt
products_cmfplone-6.1.3.dist-info/top_level.txt
products_cmfplone-6.1.3.dist-info/RECORD
