Metadata-Version: 2.2
Name: Products.CMFPlone
Version: 6.1.3
Summary: The Plone Content Management System (core)
Home-page: https://plone.org
Author: Plone Foundation
Author-email: releasemanager@plone.org
License: GPL version 2
Project-URL: Homepage, https://plone.org
Project-URL: Documentation, https://6.docs.plone.org
Project-URL: Source, https://github.com/plone/Products.CMFPlone
Project-URL: Issues, https://github.com/plone/plone.org/Products.CMFPlone
Project-URL: Forum, https://community.plone.org/
Project-URL: Chat, https://discord.gg/zFY3EBbjaj
Project-URL: Mastodon, https://plone.social/@plone
Project-URL: X (formerly Twitter), https://x.com/plone
Project-URL: Videos, https://youtube.com/@plonecms
Project-URL: Sponsor, https://github.com/sponsors/plone
Keywords: Plone CMF Python Zope CMS Webapplication
Classifier: Development Status :: 5 - Production/Stable
Classifier: Environment :: Web Environment
Classifier: Framework :: Plone
Classifier: Framework :: Plone :: 6.1
Classifier: Framework :: Plone :: Core
Classifier: Framework :: Zope :: 5
Classifier: License :: OSI Approved :: GNU General Public License v2 (GPLv2)
Classifier: Operating System :: OS Independent
Classifier: Programming Language :: Python
Classifier: Programming Language :: Python :: 3.10
Classifier: Programming Language :: Python :: 3.11
Classifier: Programming Language :: Python :: 3.12
Classifier: Programming Language :: Python :: 3.13
Requires-Python: >=3.10
License-File: LICENSE
Requires-Dist: borg.localrole
Requires-Dist: five.customerize
Requires-Dist: lxml
Requires-Dist: packaging
Requires-Dist: plone.app.content
Requires-Dist: plone.app.contentlisting
Requires-Dist: plone.app.contentmenu>=2.0.1
Requires-Dist: plone.app.contentrules
Requires-Dist: plone.app.contenttypes
Requires-Dist: plone.app.customerize
Requires-Dist: plone.app.dexterity
Requires-Dist: plone.app.i18n
Requires-Dist: plone.app.layout>=2.5.15
Requires-Dist: plone.app.linkintegrity>=1.0.3
Requires-Dist: plone.app.locales
Requires-Dist: plone.app.portlets
Requires-Dist: plone.app.redirector
Requires-Dist: plone.app.registry
Requires-Dist: plone.app.theming
Requires-Dist: plone.app.users
Requires-Dist: plone.app.uuid
Requires-Dist: plone.app.viewletmanager
Requires-Dist: plone.app.vocabularies
Requires-Dist: plone.app.workflow
Requires-Dist: plone.app.z3cform>=4.1.0
Requires-Dist: plone.base
Requires-Dist: plone.browserlayer>=2.1.5
Requires-Dist: plone.contentrules
Requires-Dist: plone.folder
Requires-Dist: plone.i18n>=4.0.5
Requires-Dist: plone.indexer
Requires-Dist: plone.intelligenttext
Requires-Dist: plone.locking
Requires-Dist: plone.memoize
Requires-Dist: plone.outputfilters
Requires-Dist: plone.portlet.collection
Requires-Dist: plone.portlet.static
Requires-Dist: plone.portlets
Requires-Dist: plone.protect>=3.0.0
Requires-Dist: plone.resource
Requires-Dist: plone.schema
Requires-Dist: plone.session
Requires-Dist: plone.staticresources
Requires-Dist: plone.theme
Requires-Dist: plonetheme.barceloneta
Requires-Dist: Products.CMFEditions
Requires-Dist: Products.DCWorkflow
Requires-Dist: Products.ExtendedPathIndex
Requires-Dist: Products.isurlinportal
Requires-Dist: Products.MimetypesRegistry
Requires-Dist: Products.PlonePAS
Requires-Dist: Products.PortalTransforms
Requires-Dist: Products.SiteErrorLog
Requires-Dist: Products.statusmessages
Requires-Dist: setuptools>=36.2
Requires-Dist: plone.autoinclude
Requires-Dist: webresource>=1.2
Requires-Dist: Zope[wsgi]>=5.0
Requires-Dist: zope.app.locales>=3.6.0
Requires-Dist: zope.cachedescriptors
Requires-Dist: zope.deferredimport
Requires-Dist: zope.deprecation
Requires-Dist: zope.dottedname
Requires-Dist: zope.i18n
Requires-Dist: zope.i18nmessageid
Requires-Dist: zope.structuredtext
Provides-Extra: test
Requires-Dist: lxml; extra == "test"
Requires-Dist: plone.app.robotframework>=1.0; extra == "test"
Requires-Dist: robotframework-debuglibrary; extra == "test"
Requires-Dist: plone.app.testing; extra == "test"
Requires-Dist: zope.globalrequest; extra == "test"
Requires-Dist: zope.testing; extra == "test"
Requires-Dist: gunicorn; extra == "test"
Dynamic: author
Dynamic: author-email
Dynamic: classifier
Dynamic: description
Dynamic: description-content-type
Dynamic: home-page
Dynamic: keywords
Dynamic: license
Dynamic: project-url
Dynamic: provides-extra
Dynamic: requires-dist
Dynamic: requires-python
Dynamic: summary
